gdbundle_gdb_dashboard/__init__.py
gdbundle_gdb_dashboard/gdb_loader.py
gdbundle_gdb_dashboard/scripts/.gitignore
gdbundle_gdb_dashboard/scripts/.keep
gdbundle_gdb_dashboard/scripts/gdb-dashboard.gdb
gdbundle_gdb_dashboard-0.11.4.post1.dist-info/WHEEL
gdbundle_gdb_dashboard-0.11.4.post1.dist-info/METADATA
gdbundle_gdb_dashboard-0.11.4.post1.dist-info/RECORD
